./.gitignore
./LICENSE
./PKG-INFO
./README.md
./USAGE.md
./main.py
./pyproject.toml
itop_mcp-1.0.2.dist-info/METADATA
itop_mcp-1.0.2.dist-info/WHEEL
itop_mcp-1.0.2.dist-info/entry_points.txt
itop_mcp-1.0.2.dist-info/licenses/LICENSE
itop_mcp-1.0.2.dist-info/RECORD
