Metadata-Version: 2.4
Name: itop-mcp
Version: 1.0.2
Summary: Model Context Protocol server for iTop ITSM integration
Project-URL: Homepage, https://github.com/roneydsilva/itop-mcp
Project-URL: Documentation, https://github.com/roneydsilva/itop-mcp#readme
Project-URL: Repository, https://github.com/roneydsilva/itop-mcp.git
Project-URL: Issues, https://github.com/roneydsilva/itop-mcp/issues
Project-URL: Changelog, https://github.com/roneydsilva/itop-mcp/releases
Author-email: Roney Dsilva <roney@cdmx.in>
Maintainer-email: Roney Dsilva <roney@cdmx.in>
License: MIT
License-File: LICENSE
Keywords: ai,assistant,claude,itop,itsm,mcp,model-context-protocol,rest-api
Classifier: Development Status :: 5 - Production/Stable
Classifier: Intended Audience :: Developers
Classifier: Intended Audience :: System Administrators
Classifier: License :: OSI Approved :: MIT License
Classifier: Operating System :: OS Independent
Classifier: Programming Language :: Python :: 3
Classifier: Programming Language :: Python :: 3.10
Classifier: Programming Language :: Python :: 3.11
Classifier: Programming Language :: Python :: 3.12
Classifier: Topic :: Communications :: Chat
Classifier: Topic :: Internet :: WWW/HTTP :: Dynamic Content
Classifier: Topic :: Software Development :: Libraries :: Python Modules
Classifier: Topic :: System :: Systems Administration
Requires-Python: >=3.10
Requires-Dist: httpx>=0.28.1
Requires-Dist: mcp[cli]>=1.9.4
Provides-Extra: dev
Requires-Dist: black>=23.0.0; extra == 'dev'
Requires-Dist: isort>=5.12.0; extra == 'dev'
Requires-Dist: mypy>=1.0.2; extra == 'dev'
Requires-Dist: pytest-asyncio>=0.21.0; extra == 'dev'
Requires-Dist: pytest>=7.0.0; extra == 'dev'
